trumpetune/__init__.py
trumpetune/__main__.py
trumpetune/_app.py
trumpetune/_loop.py
trumpetune/_utils.py
trumpetune/_ws.py
trumpetune/trumpetune-ui/favicon.png
trumpetune/trumpetune-ui/global.css
trumpetune/trumpetune-ui/index.html
trumpetune/trumpetune-ui/build/bundle.css
trumpetune/trumpetune-ui/build/bundle.js
trumpetune/trumpetune-ui/build/bundle.js.map
trumpetune-2.3.8.dist-info/LICENSE
trumpetune-2.3.8.dist-info/METADATA
trumpetune-2.3.8.dist-info/WHEEL
trumpetune-2.3.8.dist-info/entry_points.txt
trumpetune-2.3.8.dist-info/top_level.txt
trumpetune-2.3.8.dist-info/RECORD
