Metadata-Version: 2.1
Name: trumpetune
Version: 2.3.8
Summary: Serve ML inference pipelines like tunning a Trumpet.
Home-page: https://github.com/alifzl/trumpetune
Author: ALI FAZELI
Author-email: a.fazeli95@gmail.com
License: MIT
Classifier: License :: OSI Approved :: MIT License
Classifier: Programming Language :: Python
Classifier: Programming Language :: Python :: 3
Classifier: Programming Language :: Python :: 3.6
Classifier: Programming Language :: Python :: Implementation :: CPython
Requires-Python: >=3.6.0
License-File: LICENSE
Requires-Dist: requests
Requires-Dist: falcon
Requires-Dist: diskcache
Requires-Dist: ujson
Requires-Dist: gunicorn[gevent]
